dbtimer/__init__.py
dbtimer/admin.py
dbtimer/apps.py
dbtimer/conf.py
dbtimer/models.py
dbtimer/tests.py
dbtimer/utils.py
dbtimer/views.py
dbtimer/management/__init__.py
dbtimer/management/commands/__init__.py
dbtimer/management/commands/dbtimer.py
dbtimer/migrations/0001_initial.py
dbtimer/migrations/__init__.py
dbtimer/mixins/__init__.py
dbtimer/mixins/admin.py
dbtimer/mixins/models.py
dbtimer/templates/dbtimer/index.html
management/__init__.py
management/commands/__init__.py
management/commands/dbtimer.py
migrations/0001_initial.py
migrations/__init__.py
mixins/__init__.py
mixins/admin.py
mixins/models.py
src/dbtimer/__init__.py
src/dbtimer/admin.py
src/dbtimer/apps.py
src/dbtimer/conf.py
src/dbtimer/models.py
src/dbtimer/tests.py
src/dbtimer/utils.py
src/dbtimer/views.py
dbtimer-0.1.1.dist-info/LICENSE
dbtimer-0.1.1.dist-info/METADATA
dbtimer-0.1.1.dist-info/WHEEL
dbtimer-0.1.1.dist-info/top_level.txt
dbtimer-0.1.1.dist-info/RECORD
