Metadata-Version: 2.1
Name: dbtimer
Version: 0.1.1
Summary: A Django management command to measure and benchmark database query performance.
Home-page: https://bitbucket.org/dpater/dbtimer
Author: Django Web Studio
Author-email: devs@djangowebstudio.com
License: GNU
Classifier: Development Status :: 4 - Beta
Classifier: Framework :: Django
Classifier: Intended Audience :: Developers
Classifier: License :: OSI Approved :: MIT License
Classifier: Programming Language :: Python :: 3
Classifier: Programming Language :: Python :: 3.7
Classifier: Programming Language :: Python :: 3.8
Classifier: Programming Language :: Python :: 3.9
Classifier: Programming Language :: Python :: 3.10
Classifier: Programming Language :: Python :: 3.11
Requires-Python: >=3.7
License-File: LICENSE
Requires-Dist: django <5.0,>=3.2
Requires-Dist: tqdm >=4.64.0
Requires-Dist: boto3 >=1.18.0
Requires-Dist: matplotlib >=3.4.0
Requires-Dist: requests >=2.26.0
